boreal bci 2/boreal_neuro_core_v2.4/rtl/boreal_csp_filter.v
/*
 * Boreal BCI 14-Channel Common Spatial Pattern (CSP) Filter
 * 
 * Purpose:
 * Projects 14 channels of raw spatial EEG data into an N-dimensional 
 * discriminative subspace (default N=4 components).
 * 
 * Pipeline:
 * Stage 1: Register Inputs
 * Stage 2: Parallel DSP Multipliers (Q1.15 Fixed Point)
 * Stage 3: Accumulator Tree
 * Stage 4: Register Outputs
 */

module boreal_csp_filter #(
    parameter NUM_CHANNELS = 14,
    parameter NUM_COMPONENTS = 4
)(
    input  wire        clk,
    input  wire        rst_n,
    input  wire        data_valid_in,

    // 14 Channels of 16-bit Input Data
    input  wire signed [15:0] ch_in_0,
    input  wire signed [15:0] ch_in_1,
    input  wire signed [15:0] ch_in_2,
    input  wire signed [15:0] ch_in_3,
    input  wire signed [15:0] ch_in_4,
    input  wire signed [15:0] ch_in_5,
    input  wire signed [15:0] ch_in_6,
    input  wire signed [15:0] ch_in_7,
    input  wire signed [15:0] ch_in_8,
    input  wire signed [15:0] ch_in_9,
    input  wire signed [15:0] ch_in_10,
    input  wire signed [15:0] ch_in_11,
    input  wire signed [15:0] ch_in_12,
    input  wire signed [15:0] ch_in_13,

    // Projection Weights Matrix: W[NUM_COMPONENTS][NUM_CHANNELS]
    // In production, this can be mapped to block RAM or AXI registers
    // using continuous assignments or memory initialization.
    // For this module we assume they are provided as stable inputs contextually.
    
    // N discriminative output components
    output reg signed [15:0] comp_out_0,
    output reg signed [15:0] comp_out_1,
    output reg signed [15:0] comp_out_2,
    output reg signed [15:0] comp_out_3,
    output reg               data_valid_out
);

    // Hardcoded Example Weights (Q1.15 Format)
    // These would normally be loaded dynamically via SPI/AXI after Python training
    // Format: W[component][channel]
    // 0x7FFF = ~0.999, 0x0000 = 0.0, 0x8000 = -1.0
    wire signed [15:0] W_0 [0:13];
    wire signed [15:0] W_1 [0:13];
    wire signed [15:0] W_2 [0:13];
    wire signed [15:0] W_3 [0:13];

    // Dummy Weights for Compilation (Identity/Combinatorial approximations)
    assign W_0[0] = 16'h7FFF; assign W_0[1] = 16'h4000; assign W_0[2] = 16'h2000; assign W_0[3] = 16'h1000; assign W_0[4] = 16'h0000; assign W_0[5] = 16'h0000; assign W_0[6] = 16'h0000; assign W_0[7] = 16'h0000; assign W_0[8] = 16'h0000; assign W_0[9] = 16'h0000; assign W_0[10] = 16'h0000; assign W_0[11] = 16'h0000; assign W_0[12] = 16'h0000; assign W_0[13] = 16'h8000;
    assign W_1[0] = 16'h0000; assign W_1[1] = 16'h0000; assign W_1[2] = 16'h0000; assign W_1[3] = 16'h0000; assign W_1[4] = 16'h7FFF; assign W_1[5] = 16'h4000; assign W_1[6] = 16'h2000; assign W_1[7] = 16'h0000; assign W_1[8] = 16'h0000; assign W_1[9] = 16'h0000; assign W_1[10] = 16'h0000; assign W_1[11] = 16'h0000; assign W_1[12] = 16'h8000; assign W_1[13] = 16'h8000;
    assign W_2[0] = 16'h0000; assign W_2[1] = 16'h8000; assign W_2[2] = 16'h0000; assign W_2[3] = 16'h0000; assign W_2[4] = 16'h0000; assign W_2[5] = 16'h0000; assign W_2[6] = 16'h0000; assign W_2[7] = 16'h7FFF; assign W_2[8] = 16'h4000; assign W_2[9] = 16'h2000; assign W_2[10] = 16'h0000; assign W_2[11] = 16'h0000; assign W_2[12] = 16'h0000; assign W_2[13] = 16'h0000;
    assign W_3[0] = 16'h8000; assign W_3[1] = 16'h8000; assign W_3[2] = 16'h8000; assign W_3[3] = 16'h0000; assign W_3[4] = 16'h0000; assign W_3[5] = 16'h0000; assign W_3[6] = 16'h0000; assign W_3[7] = 16'h0000; assign W_3[8] = 16'h0000; assign W_3[9] = 16'h0000; assign W_3[10] = 16'h7FFF; assign W_3[11] = 16'h4000; assign W_3[12] = 16'h2000; assign W_3[13] = 16'h1000;

    // ------------------------------------------------------------------
    // STAGE 1: Input Registering (Isolate from cross-module timing paths)
    // ------------------------------------------------------------------
    reg signed [15:0] reg_ch_in [0:13];
    reg               reg_valid_stg1;

    always @(posedge clk or negedge rst_n) begin
        if (!rst_n) begin
            reg_valid_stg1 <= 0;
            for (integer i=0; i<14; i=i+1) reg_ch_in[i] <= 0;
        end else begin
            reg_valid_stg1 <= data_valid_in;
            if (data_valid_in) begin
                reg_ch_in[0]  <= ch_in_0;
                reg_ch_in[1]  <= ch_in_1;
                reg_ch_in[2]  <= ch_in_2;
                reg_ch_in[3]  <= ch_in_3;
                reg_ch_in[4]  <= ch_in_4;
                reg_ch_in[5]  <= ch_in_5;
                reg_ch_in[6]  <= ch_in_6;
                reg_ch_in[7]  <= ch_in_7;
                reg_ch_in[8]  <= ch_in_8;
                reg_ch_in[9]  <= ch_in_9;
                reg_ch_in[10] <= ch_in_10;
                reg_ch_in[11] <= ch_in_11;
                reg_ch_in[12] <= ch_in_12;
                reg_ch_in[13] <= ch_in_13;
            end
        end
    end

    // ------------------------------------------------------------------
    // STAGE 2: Multipliers 
    // Q1.15 * Q1.15 = Q2.30 -> Shift back to Q1.15
    // ------------------------------------------------------------------
    reg signed [31:0] mult_0 [0:13];
    reg signed [31:0] mult_1 [0:13];
    reg signed [31:0] mult_2 [0:13];
    reg signed [31:0] mult_3 [0:13];
    reg               reg_valid_stg2;

    always @(posedge clk or negedge rst_n) begin
        if (!rst_n) begin
            reg_valid_stg2 <= 0;
            for (integer i=0; i<14; i=i+1) begin
                mult_0[i] <= 0; mult_1[i] <= 0; mult_2[i] <= 0; mult_3[i] <= 0;
            end
        end else begin
            reg_valid_stg2 <= reg_valid_stg1;
            if (reg_valid_stg1) begin
                for (integer i=0; i<14; i=i+1) begin
                    mult_0[i] <= reg_ch_in[i] * W_0[i];
                    mult_1[i] <= reg_ch_in[i] * W_1[i];
                    mult_2[i] <= reg_ch_in[i] * W_2[i];
                    mult_3[i] <= reg_ch_in[i] * W_3[i];
                end
            end
        end
    end

    // ------------------------------------------------------------------
    // STAGE 3 & 4: Accumulation & Output Normalization
    // ------------------------------------------------------------------
    reg signed [31:0] acc_0, acc_1, acc_2, acc_3;

    always @(posedge clk or negedge rst_n) begin
        if (!rst_n) begin
            data_valid_out <= 0;
            comp_out_0 <= 0;
            comp_out_1 <= 0;
            comp_out_2 <= 0;
            comp_out_3 <= 0;
        end else begin
            data_valid_out <= reg_valid_stg2;
            if (reg_valid_stg2) begin
                
                // Note: In an unrolled accumulator loop for latency priority
                acc_0 = mult_0[0] + mult_0[1] + mult_0[2] + mult_0[3] + mult_0[4] + mult_0[5] + mult_0[6] + 
                        mult_0[7] + mult_0[8] + mult_0[9] + mult_0[10] + mult_0[11] + mult_0[12] + mult_0[13];
                        
                acc_1 = mult_1[0] + mult_1[1] + mult_1[2] + mult_1[3] + mult_1[4] + mult_1[5] + mult_1[6] + 
                        mult_1[7] + mult_1[8] + mult_1[9] + mult_1[10] + mult_1[11] + mult_1[12] + mult_1[13];
                        
                acc_2 = mult_2[0] + mult_2[1] + mult_2[2] + mult_2[3] + mult_2[4] + mult_2[5] + mult_2[6] + 
                        mult_2[7] + mult_2[8] + mult_2[9] + mult_2[10] + mult_2[11] + mult_2[12] + mult_2[13];
                        
                acc_3 = mult_3[0] + mult_3[1] + mult_3[2] + mult_3[3] + mult_3[4] + mult_3[5] + mult_3[6] + 
                        mult_3[7] + mult_3[8] + mult_3[9] + mult_3[10] + mult_3[11] + mult_3[12] + mult_3[13];

                // Shift from Q2.30 accumulator back down to Q1.15
                // And simple saturation check
                
                // Comp 0
                if ((acc_0 >>> 15) > 32767) comp_out_0 <= 32767;
                else if ((acc_0 >>> 15) < -32768) comp_out_0 <= -32768;
                else comp_out_0 <= (acc_0 >>> 15);
                
                // Comp 1
                if ((acc_1 >>> 15) > 32767) comp_out_1 <= 32767;
                else if ((acc_1 >>> 15) < -32768) comp_out_1 <= -32768;
                else comp_out_1 <= (acc_1 >>> 15);

                // Comp 2
                if ((acc_2 >>> 15) > 32767) comp_out_2 <= 32767;
                else if ((acc_2 >>> 15) < -32768) comp_out_2 <= -32768;
                else comp_out_2 <= (acc_2 >>> 15);

                // Comp 3
                if ((acc_3 >>> 15) > 32767) comp_out_3 <= 32767;
                else if ((acc_3 >>> 15) < -32768) comp_out_3 <= -32768;
                else comp_out_3 <= (acc_3 >>> 15);

            end
        end
    end

endmodule

boreal bci 2/boreal_neuro_core_v2.4/sim/tb_boreal_csp_filter.v
`timescale 1ns / 1ps

module tb_boreal_csp_filter;

    // Inputs
    reg clk;
    reg rst_n;
    reg data_valid_in;
    reg signed [15:0] ch_in [0:13];

    // Outputs
    wire signed [15:0] comp_out_0;
    wire signed [15:0] comp_out_1;
    wire signed [15:0] comp_out_2;
    wire signed [15:0] comp_out_3;
    wire data_valid_out;

    // Instantiate UUT
    boreal_csp_filter uut (
        .clk(clk),
        .rst_n(rst_n),
        .data_valid_in(data_valid_in),
        .ch_in_0(ch_in[0]),
        .ch_in_1(ch_in[1]),
        .ch_in_2(ch_in[2]),
        .ch_in_3(ch_in[3]),
        .ch_in_4(ch_in[4]),
        .ch_in_5(ch_in[5]),
        .ch_in_6(ch_in[6]),
        .ch_in_7(ch_in[7]),
        .ch_in_8(ch_in[8]),
        .ch_in_9(ch_in[9]),
        .ch_in_10(ch_in[10]),
        .ch_in_11(ch_in[11]),
        .ch_in_12(ch_in[12]),
        .ch_in_13(ch_in[13]),
        .comp_out_0(comp_out_0),
        .comp_out_1(comp_out_1),
        .comp_out_2(comp_out_2),
        .comp_out_3(comp_out_3),
        .data_valid_out(data_valid_out)
    );

    // Clock gen
    always #5 clk = ~clk;

    // Task to apply stimulus
    task apply_snapshot;
        input signed [15:0] in0, in1, in2, in3, in4, in5, in6, in7, in8, in9, in10, in11, in12, in13;
        begin
            @(posedge clk);
            data_valid_in = 1;
            ch_in[0] = in0; ch_in[1] = in1; ch_in[2] = in2; ch_in[3] = in3;
            ch_in[4] = in4; ch_in[5] = in5; ch_in[6] = in6; ch_in[7] = in7;
            ch_in[8] = in8; ch_in[9] = in9; ch_in[10] = in10; ch_in[11] = in11;
            ch_in[12] = in12; ch_in[13] = in13;
            @(posedge clk);
            data_valid_in = 0;
            // Wait for pipeline depth (3 cycles minimum: register, mult, accum/shift)
            #30; 
        end
    endtask

    initial begin
        // Init
        clk = 0;
        rst_n = 0;
        data_valid_in = 0;
        for(integer i=0; i<14; i=i+1) ch_in[i] = 0;

        $dumpfile("sim/boreal_csp.vcd");
        $dumpvars(0, tb_boreal_csp_filter);

        // Reset
        #100;
        rst_n = 1;
        #10;

        $display("=== BOREAL CSP FILTER SIMULATION ===");
        
        // ---------------------------------------------------------
        // Test 1: Zeros
        // Expected: All 0s
        // ---------------------------------------------------------
        apply_snapshot(0, 0, 0, 0, 0, 0, 0, 0, 0, 0, 0, 0, 0, 0);
        $display("T1 (Zeros)   -> Comp0: %d, Comp1: %d, Comp2: %d, Comp3: %d", comp_out_0, comp_out_1, comp_out_2, comp_out_3);

        // ---------------------------------------------------------
        // Test 2: Target Comp 0 (Weights: 0: ~1.0, 1: 0.5, 2: 0.25, 3: 0.125, 13: -1.0)
        // Input: 0=1000, 1=1000, 2=1000, 3=1000, 13=-1000
        // Expected Comp0: 1000*(1 + .5 + .25 + .125 + 1) ~= 2875
        // Expected Others: ~0 or slight noise depending on weight matrix overlaps
        // ---------------------------------------------------------
        apply_snapshot(1000, 1000, 1000, 1000, 0, 0, 0, 0, 0, 0, 0, 0, 0, -1000);
        $display("T2 (Comp 0)  -> Comp0: %d, Comp1: %d, Comp2: %d, Comp3: %d", comp_out_0, comp_out_1, comp_out_2, comp_out_3);

        // ---------------------------------------------------------
        // Test 3: Target Comp 1 (Weights: 4: ~1.0, 5: 0.5, 6: 0.25, 12: -1.0, 13: -1.0)
        // Input: 4=2000, 5=2000, 6=2000, 12=-1000, 13=-1000
        // Expected Comp1: 2000*(1 + .5 + .25) -1000*(-1) -1000*(-1) = 3500 + 1000 + 1000 = 5500
        // ---------------------------------------------------------
        apply_snapshot(0, 0, 0, 0, 2000, 2000, 2000, 0, 0, 0, 0, 0, -1000, -1000);
        $display("T3 (Comp 1)  -> Comp0: %d, Comp1: %d, Comp2: %d, Comp3: %d", comp_out_0, comp_out_1, comp_out_2, comp_out_3);

        // ---------------------------------------------------------
        // Test 4: Maximum Negative Input (Edge case saturation test against Comp 3)
        // Weight Comp 3: 0:-1.0, 1:-1.0, 2:-1.0, 10:1.0, 11:0.5, 12:0.25, 13:0.125
        // Input everything to -32768
        // Expected: Saturation clamp at -32768 or 32767
        // ---------------------------------------------------------
        apply_snapshot(-32768, -32768, -32768, -32768, -32768, -32768, -32768, -32768, -32768, -32768, -32768, -32768, -32768, -32768);
        $display("T4 (Max Neg) -> Comp0: %d, Comp1: %d, Comp2: %d, Comp3: %d", comp_out_0, comp_out_1, comp_out_2, comp_out_3);

        $display("=== SIMULATION COMPLETE ===");
        $finish;
    end

endmodule

boreal bci 2/boreal_neuro_core_v2.4/sim/boreal_csp.vcd
$date
	Tue Feb 24 14:16:32 2026
$end
$version
	Icarus Verilog
$end
$timescale
	1ps
$end
$scope module tb_boreal_csp_filter $end
$var wire 1 ! data_valid_out $end
$var wire 16 " comp_out_3 [15:0] $end
$var wire 16 # comp_out_2 [15:0] $end
$var wire 16 $ comp_out_1 [15:0] $end
$var wire 16 % comp_out_0 [15:0] $end
$var reg 1 & clk $end
$var reg 1 ' data_valid_in $end
$var reg 1 ( rst_n $end
$scope module uut $end
$var wire 16 ) ch_in_0 [15:0] $end
$var wire 16 * ch_in_1 [15:0] $end
$var wire 16 + ch_in_10 [15:0] $end
$var wire 16 , ch_in_11 [15:0] $end
$var wire 16 - ch_in_12 [15:0] $end
$var wire 16 . ch_in_13 [15:0] $end
$var wire 16 / ch_in_2 [15:0] $end
$var wire 16 0 ch_in_3 [15:0] $end
$var wire 16 1 ch_in_4 [15:0] $end
$var wire 16 2 ch_in_5 [15:0] $end
$var wire 16 3 ch_in_6 [15:0] $end
$var wire 16 4 ch_in_7 [15:0] $end
$var wire 16 5 ch_in_8 [15:0] $end
$var wire 16 6 ch_in_9 [15:0] $end
$var wire 1 & clk $end
$var wire 1 ' data_valid_in $end
$var wire 1 ( rst_n $end
$var parameter 32 7 NUM_CHANNELS $end
$var parameter 32 8 NUM_COMPONENTS $end
$var reg 32 9 acc_0 [31:0] $end
$var reg 32 : acc_1 [31:0] $end
$var reg 32 ; acc_2 [31:0] $end
$var reg 32 < acc_3 [31:0] $end
$var reg 16 = comp_out_0 [15:0] $end
$var reg 16 > comp_out_1 [15:0] $end
$var reg 16 ? comp_out_2 [15:0] $end
$var reg 16 @ comp_out_3 [15:0] $end
$var reg 1 ! data_valid_out $end
$var reg 1 A reg_valid_stg1 $end
$var reg 1 B reg_valid_stg2 $end
$scope begin $ivl_for_loop1 $end
$var integer 32 C i [31:0] $end
$upscope $end
$scope begin $ivl_for_loop2 $end
$var integer 32 D i [31:0] $end
$upscope $end
$scope begin $ivl_for_loop3 $end
$var integer 32 E i [31:0] $end
$upscope $end
$upscope $end
$scope begin $ivl_for_loop0 $end
$var integer 32 F i [31:0] $end
$upscope $end
$scope task apply_snapshot $end
$var reg 16 G in0 [15:0] $end
$var reg 16 H in1 [15:0] $end
$var reg 16 I in10 [15:0] $end
$var reg 16 J in11 [15:0] $end
$var reg 16 K in12 [15:0] $end
$var reg 16 L in13 [15:0] $end
$var reg 16 M in2 [15:0] $end
$var reg 16 N in3 [15:0] $end
$var reg 16 O in4 [15:0] $end
$var reg 16 P in5 [15:0] $end
$var reg 16 Q in6 [15:0] $end
$var reg 16 R in7 [15:0] $end
$var reg 16 S in8 [15:0] $end
$var reg 16 T in9 [15:0] $end
$upscope $end
$upscope $end
$enddefinitions $end
$comment Show the parameter values. $end
$dumpall
b100 8
b1110 7
$end
#0
$dumpvars
bx T
bx S
bx R
bx Q
bx P
bx O
bx N
bx M
bx L
bx K
bx J
bx I
bx H
bx G
b1110 F
bx E
b1110 D
b1110 C
0B
0A
b0 @
b0 ?
b0 >
b0 =
bx <
bx ;
bx :
bx 9
b0 6
b0 5
b0 4
b0 3
b0 2
b0 1
b0 0
b0 /
b0 .
b0 -
b0 ,
b0 +
b0 *
b0 )
0(
0'
0&
b0 %
b0 $
b0 #
b0 "
0!
$end
#5000
b1110 D
b1110 C
1&
#10000
0&
#15000
b1110 D
b1110 C
1&
#20000
0&
#25000
b1110 D
b1110 C
1&
#30000
0&
#35000
b1110 D
b1110 C
1&
#40000
0&
#45000
b1110 D
b1110 C
1&
#50000
0&
#55000
b1110 D
b1110 C
1&
#60000
0&
#65000
b1110 D
b1110 C
1&
#70000
0&
#75000
b1110 D
b1110 C
1&
#80000
0&
#85000
b1110 D
b1110 C
1&
#90000
0&
#95000
b1110 D
b1110 C
1&
#100000
0&
1(
#105000
1&
#110000
0&
b0 L
b0 K
b0 J
b0 I
b0 T
b0 S
b0 R
b0 Q
b0 P
b0 O
b0 N
b0 M
b0 H
b0 G
#115000
1A
1'
1&
#120000
0&
#125000
0A
1B
b1110 E
0'
1&
#130000
0&
#135000
1!
0B
b0 <
b0 ;
b0 :
b0 9
1&
#140000
0&
#145000
0!
1&
#150000
0&
#155000
1A
b1111110000011000 .
b1111101000 0
b1111101000 /
b1111101000 *
b1111101000 )
1'
1&
b1111110000011000 L
b1111101000 N
b1111101000 M
b1111101000 H
b1111101000 G
#160000
0&
#165000
1B
0A
b1110 E
0'
1&
#170000
0&
#175000
b1111001111001011 "
b1111001111001011 @
b1111110000011000 #
b1111110000011000 ?
b1111101000 $
b1111101000 >
b101100111010 %
b101100111010 =
1!
0B
b11111001111001011000000000000000 <
b11111110000011000000000000000000 ;
b1111101000000000000000000 :
b101100111010111110000011000 9
1&
#180000
0&
#185000
0!
1&
#190000
0&
#195000
1A
b1111110000011000 -
b11111010000 3
b11111010000 2
b11111010000 1
b0 0
b0 /
b0 *
b0 )
1'
1&
b1111110000011000 K
b11111010000 Q
b11111010000 P
b11111010000 O
b0 N
b0 M
b0 H
b0 G
#200000
0&
#205000
1B
0A
b1110 E
0'
1&
#210000
0&
#215000
b1111111010001001 "
b1111111010001001 @
b0 #
b0 ?
b1010101111011 $
b1010101111011 >
b1111101000 %
b1111101000 =
1!
0B
b11111111010001001000000000000000 <
b0 ;
b1010101111011111100000110000 :
b1111101000000000000000000 9
1&
#220000
0&
#225000
0!
1&
#230000
0&
#235000
1A
b1000000000000000 .
b1000000000000000 -
b1000000000000000 ,
b1000000000000000 +
b1000000000000000 6
b1000000000000000 5
b1000000000000000 4
b1000000000000000 3
b1000000000000000 2
b1000000000000000 1
b1000000000000000 0
b1000000000000000 /
b1000000000000000 *
b1000000000000000 )
1'
1&
b1000000000000000 L
b1000000000000000 K
b1000000000000000 J
b1000000000000000 I
b1000000000000000 T
b1000000000000000 S
b1000000000000000 R
b1000000000000000 Q
b1000000000000000 P
b1000000000000000 O
b1000000000000000 N
b1000000000000000 M
b1000000000000000 H
b1000000000000000 G
#240000
0&
#245000
1B
0A
b1110 E
0'
1&
#250000
0&
#255000
b111111111111111 "
b111111111111111 @
b1010000000000001 #
b1010000000000001 ?
b10000000000001 $
b10000000000001 >
b1001000000000001 %
b1001000000000001 =
1!
0B
b1001000000000001000000000000000 <
b11010000000000001000000000000000 ;
b10000000000001000000000000000 :
b11001000000000001000000000000000 9
1&
#260000
0&
#265000
0!
1&
