boreal bci 2/boreal_neuro_core_v2.4/rtl/boreal_kalman_filter.v
/*
 * Boreal BCI 1D Steady-State Kalman Filter (Alpha-Beta Filter)
 * 
 * Purpose:
 * Provides optimal recursive state estimation (position and velocity) for 
 * a single spatial dimension, drastically smoothing noisy EEG control signals 
 * without introducing the severe phase-lag typical of IIR/FIR low-pass filters.
 *
 * Algorithm (Alpha-Beta Approximation of Kalman Filter):
 * Predict Step:
 *   x_pred = x_est_prev + v_est_prev * dt
 *   v_pred = v_est_prev
 * 
 * Update Step (Measurement):
 *   residual = measurement - x_pred
 *   x_est = x_pred + alpha * residual
 *   v_est = v_pred + (beta / dt) * residual
 * 
 * Note: dt is abstracted into the Beta coefficient (Beta_prime = Beta / dt)
 * for fixed-point hardware efficiency.
 */

module boreal_kalman_filter (
    input  wire        clk,
    input  wire        rst_n,
    input  wire        enable,
    
    // Raw noisy measurement from the CSP or inference stage
    input  wire signed [15:0] measurement_in,
    input  wire               valid_in,

    // Kalman gain coefficients (Q1.15 Fixed Point)
    // 0x7FFF = ~0.999, 0x0100 = ~0.0078
    // Typical values for BCI: Alpha = 0.2 (0x1999), Beta' = 0.05 (0x0666)
    input  wire signed [15:0] alpha_gain,
    input  wire signed [15:0] beta_gain,

    // Optimally smoothed state outputs
    output reg signed [15:0] position_out,
    output reg signed [15:0] velocity_out,
    output reg               valid_out
);

    // Internal State Registers (Q1.15)
    reg signed [31:0] x_est; // Position
    reg signed [31:0] v_est; // Velocity

    // Combinatorial prediction nodes
    reg signed [31:0] x_pred;
    reg signed [31:0] v_pred;
    reg signed [31:0] residual;

    // Fixed-point scaling constant
    localparam FP_SHIFT = 15;

    always @(posedge clk or negedge rst_n) begin
        if (!rst_n) begin
            x_est <= 0;
            v_est <= 0;
            position_out <= 0;
            velocity_out <= 0;
            valid_out <= 0;
        end else if (enable) begin
            if (valid_in) begin
                // 1. Predict Step
                // x_pred = x_est + v_est
                // v_pred = v_est
                x_pred = x_est + v_est;
                v_pred = v_est;

                // 2. Calculate Residual (Innovation)
                // residual = measurement - x_pred
                // Note: Sign-extend measurement to 32 bits for math
                residual = {{16{measurement_in[15]}}, measurement_in} - x_pred;

                // 3. Update Step
                // Multiply coefficients: (Q1.15 * Q1.15) >> 15 = Q1.15
                // x_est = x_pred + (alpha * residual)
                // v_est = v_pred + (beta * residual)
                
                // Temporary registers for DSP multiplication results
                // Using 64-bit to prevent intermediate overflow during multiply of 32-bit residual
                // We truncate back to 32 bits after the shift.
                
                // Inline math for FPGA DSP synthesis
                x_est <= x_pred + (($signed(alpha_gain) * residual) >>> FP_SHIFT);
                v_est <= v_pred + (($signed(beta_gain)  * residual) >>> FP_SHIFT);

                // 4. Output assignment with saturation prevention
                // In typical BCI, position shouldn't exceed 16-bit limits
                position_out <= x_pred[15:0] + (($signed(alpha_gain) * residual) >>> FP_SHIFT);
                velocity_out <= v_pred[15:0] + (($signed(beta_gain)  * residual) >>> FP_SHIFT);

                valid_out <= 1;
            end else begin
                valid_out <= 0;
            end
        end else begin
            // Disabled: hold outputs, hold state
            valid_out <= 0;
        end
    end

endmodule

boreal bci 2/boreal_neuro_core_v2.4/sim/tb_boreal_kalman_filter.v
`timescale 1ns / 1ps

module tb_boreal_kalman_filter;

    // Inputs
    reg clk;
    reg rst_n;
    reg enable;
    reg signed [15:0] measurement_in;
    reg valid_in;
    reg signed [15:0] alpha_gain;
    reg signed [15:0] beta_gain;

    // Outputs
    wire signed [15:0] position_out;
    wire signed [15:0] velocity_out;
    wire valid_out;

    // Instantiate UUT
    boreal_kalman_filter uut (
        .clk(clk),
        .rst_n(rst_n),
        .enable(enable),
        .measurement_in(measurement_in),
        .valid_in(valid_in),
        .alpha_gain(alpha_gain),
        .beta_gain(beta_gain),
        .position_out(position_out),
        .velocity_out(velocity_out),
        .valid_out(valid_out)
    );

    // Clock gen (100MHz)
    always #5 clk = ~clk;

    // Helper task to apply a measurement
    task apply_measurement;
        input signed [15:0] z;
        begin
            @(posedge clk);
            valid_in = 1;
            measurement_in = z;
            @(posedge clk);
            if (!enable) begin // Emulate module behavior
               valid_in = 0;
            end
            @(posedge clk);
            valid_in = 0;
            #20; // Allow state to update
        end
    endtask

    initial begin
        // Initialize
        clk = 0;
        rst_n = 0;
        enable = 0;
        measurement_in = 0;
        valid_in = 0;
        
        // Typical BCI parameters (Alpha=0.2, Beta=0.01)
        // Alpha = 0.2 * 32768 = 6553.6 -> 16'h1999
        alpha_gain = 16'h1999;
        // Beta = 0.01 * 32768 = 327.68 -> 16'h0147
        beta_gain = 16'h0147;

        $dumpfile("sim/boreal_kalman.vcd");
        $dumpvars(0, tb_boreal_kalman_filter);

        #100;
        rst_n = 1;
        #20;
        enable = 1;

        $display("=== BOREAL KALMAN FILTER SIMULATION ===");
        
        // ---------------------------------------------------------
        // Test 1: Step Response (Jumps from 0 to 1000)
        // Expected: Position asymptotically approaches 1000 without overshoot 
        // ---------------------------------------------------------
        $display("--- Test 1: Step Response (Z=1000) ---");
        apply_measurement(1000);
        $display("T=1 | Meas: 1000 | Pos: %d | Vel: %d", position_out, velocity_out);
        apply_measurement(1000);
        $display("T=2 | Meas: 1000 | Pos: %d | Vel: %d", position_out, velocity_out);
        apply_measurement(1000);
        $display("T=3 | Meas: 1000 | Pos: %d | Vel: %d", position_out, velocity_out);
        apply_measurement(1000);
        $display("T=4 | Meas: 1000 | Pos: %d | Vel: %d", position_out, velocity_out);
        apply_measurement(1000);
        $display("T=5 | Meas: 1000 | Pos: %d | Vel: %d", position_out, velocity_out);
        
        // ---------------------------------------------------------
        // Test 2: High-Frequency Noise Rejection 
        // ---------------------------------------------------------
        $display("--- Test 2: High-Frequency Noise Spike ---");
        // Simulate a massive artifact (e.g., eye blink or muscle twitch)
        apply_measurement(15000); 
        $display("T=6 | Meas: 15000 | Pos: %d | Vel: %d", position_out, velocity_out);
        
        // Return to baseline immediately
        apply_measurement(1000); 
        $display("T=7 | Meas: 1000 | Pos: %d | Vel: %d", position_out, velocity_out);
        apply_measurement(1000);
        $display("T=8 | Meas: 1000 | Pos: %d | Vel: %d", position_out, velocity_out);

        // ---------------------------------------------------------
        // Test 3: Tracking a moving target (Velocity estimation)
        // ---------------------------------------------------------
        $display("--- Test 3: Ramp Tracking ---");
        apply_measurement(1100); $display("T=9  | Pos: %d | Vel: %d", position_out, velocity_out);
        apply_measurement(1200); $display("T=10 | Pos: %d | Vel: %d", position_out, velocity_out);
        apply_measurement(1300); $display("T=11 | Pos: %d | Vel: %d", position_out, velocity_out);
        apply_measurement(1400); $display("T=12 | Pos: %d | Vel: %d", position_out, velocity_out);
        apply_measurement(1500); $display("T=13 | Pos: %d | Vel: %d", position_out, velocity_out);
        apply_measurement(1600); $display("T=14 | Pos: %d | Vel: %d", position_out, velocity_out);

        $display("=== SIMULATION COMPLETE ===");
        $finish;
    end

endmodule

boreal bci 2/boreal_neuro_core_v2.4/sim/boreal_kalman.vcd
$date
	Tue Feb 24 14:22:06 2026
$end
$version
	Icarus Verilog
$end
$timescale
	1ps
$end
$scope module tb_boreal_kalman_filter $end
$var wire 16 ! velocity_out [15:0] $end
$var wire 1 " valid_out $end
$var wire 16 # position_out [15:0] $end
$var reg 16 $ alpha_gain [15:0] $end
$var reg 16 % beta_gain [15:0] $end
$var reg 1 & clk $end
$var reg 1 ' enable $end
$var reg 16 ( measurement_in [15:0] $end
$var reg 1 ) rst_n $end
$var reg 1 * valid_in $end
$scope module uut $end
$var wire 16 + alpha_gain [15:0] $end
$var wire 16 , beta_gain [15:0] $end
$var wire 1 & clk $end
$var wire 1 ' enable $end
$var wire 16 - measurement_in [15:0] $end
$var wire 1 ) rst_n $end
$var wire 1 * valid_in $end
$var parameter 32 . FP_SHIFT $end
$var reg 16 / position_out [15:0] $end
$var reg 32 0 residual [31:0] $end
$var reg 32 1 v_est [31:0] $end
$var reg 32 2 v_pred [31:0] $end
$var reg 1 " valid_out $end
$var reg 16 3 velocity_out [15:0] $end
$var reg 32 4 x_est [31:0] $end
$var reg 32 5 x_pred [31:0] $end
$upscope $end
$scope task apply_measurement $end
$var reg 16 6 z [15:0] $end
$upscope $end
$upscope $end
$enddefinitions $end
$comment Show the parameter values. $end
$dumpall
b1111 .
$end
#0
$dumpvars
bx 6
bx 5
b0 4
b0 3
bx 2
b0 1
bx 0
b0 /
b0 -
b101000111 ,
b1100110011001 +
0*
0)
b0 (
0'
0&
b101000111 %
b1100110011001 $
b0 #
0"
b0 !
$end
#5000
1&
#10000
0&
#15000
1&
#20000
0&
#25000
1&
#30000
0&
#35000
1&
#40000
0&
#45000
1&
#50000
0&
#55000
1&
#60000
0&
#65000
1&
#70000
0&
#75000
1&
#80000
0&
#85000
1&
#90000
0&
#95000
1&
#100000
0&
1)
#105000
1&
#110000
0&
#115000
1&
#120000
0&
b1111101000 6
1'
#125000
1"
b1001 !
b1001 3
b11000111 #
b11000111 /
b1001 1
b11000111 4
b1111101000 0
b0 2
b0 5
b1111101000 (
b1111101000 -
1*
1&
#130000
0&
#135000
b10000 !
b10000 3
b101101110 #
b101101110 /
b10000 1
b101101110 4
b1100011000 0
b1001 2
b11010000 5
1&
#140000
0&
#145000
0"
0*
1&
#150000
0&
#155000
1&
#160000
0&
#165000
1"
b10110 !
b10110 3
b111111001 #
b111111001 /
b10110 1
b111111001 4
b1001101010 0
b10000 2
b101111110 5
1*
1&
#170000
0&
#175000
b11010 !
b11010 3
b1001101101 #
b1001101101 /
b11010 1
b1001101101 4
b111011001 0
b10110 2
b1000001111 5
1&
#180000
0&
#185000
0"
0*
1&
#190000
0&
#195000
1&
#200000
0&
#205000
1"
b11101 !
b11101 3
b1011001101 #
b1011001101 /
b11101 1
b1011001101 4
b101100001 0
b11010 2
b1010000111 5
1*
1&
#210000
0&
#215000
b11111 !
b11111 3
b1100011100 #
b1100011100 /
b11111 1
b1100011100 4
b11111110 0
b11101 2
b1011101010 5
1&
#220000
0&
#225000
0"
0*
1&
#230000
0&
#235000
1&
#240000
0&
#245000
1"
b100000 !
b100000 3
b1101011101 #
b1101011101 /
b100000 1
b1101011101 4
b10101101 0
b11111 2
b1100111011 5
1*
1&
#250000
0&
#255000
b100001 !
b100001 3
b1110010010 #
b1110010010 /
b100001 1
b1110010010 4
b1101011 0
b100000 2
b1101111101 5
1&
#260000
0&
#265000
0"
0*
1&
#270000
0&
#275000
1&
#280000
0&
#285000
1"
b1110111101 #
b1110111101 /
b1110111101 4
b110101 0
b100001 2
b1110110011 5
1*
1&
#290000
0&
#295000
b1111011111 #
b1111011111 /
b1111011111 4
b1010 0
b1111011110 5
1&
#300000
0&
#305000
0"
0*
1&
#310000
0&
#315000
1&
#320000
0&
#325000
1"
b10101100 !
b10101100 3
b111011101010 #
b111011101010 /
b10101100 1
b111011101010 4
b11011010011000 0
b10000000000 5
b11101010011000 (
b11101010011000 -
1*
1&
b11101010011000 6
#330000
0&
#335000
b100011001 !
b100011001 3
b1100000101111 #
b1100000101111 /
b100011001 1
b1100000101111 4
b10101100000010 0
b10101100 2
b111110010110 5
1&
#340000
0&
#345000
0"
0*
1&
#350000
0&
#355000
1&
#360000
0&
#365000
1"
b11100010 !
b11100010 3
b1010100000001 #
b1010100000001 /
b11100010 1
b1010100000001 4
b11111111111111111110101010100000 0
b100011001 2
b1100101001000 5
b1111101000 (
b1111101000 -
1*
1&
b1111101000 6
#370000
0&
#375000
b10110100 !
b10110100 3
b1001001001010 #
b1001001001010 /
b10110100 1
b1001001001010 4
b11111111111111111110111000000101 0
b11100010 2
b1010111100011 5
1&
#380000
0&
#385000
0"
0*
1&
#390000
0&
#395000
1&
#400000
0&
#405000
1"
b10001101 !
b10001101 3
b111111111001 #
b111111111001 /
b10001101 1
b111111111001 4
b11111111111111111111000011101010 0
b10110100 2
b1001011111110 5
1*
1&
#410000
0&
#415000
b1101100 !
b1101100 3
b111000000000 #
b111000000000 /
b1101100 1
b111000000000 4
b11111111111111111111001101100010 0
b10001101 2
b1000010000110 5
1&
#420000
0&
#425000
0"
0*
1&
#430000
0&
#435000
1&
#440000
0&
#445000
1"
b1010010 !
b1010010 3
b110001100101 #
b110001100101 /
b1010010 1
b110001100101 4
b11111111111111111111010111100000 0
b1101100 2
b111001101100 5
b10001001100 (
b10001001100 -
1*
1&
b10001001100 6
#450000
0&
#455000
b111100 !
b111100 3
b101100001000 #
b101100001000 /
b111100 1
b101100001000 4
b11111111111111111111011110010101 0
b1010010 2
b110010110111 5
1&
#460000
0&
#465000
0"
0*
1&
#470000
0&
#475000
1&
#480000
0&
#485000
1"
b101011 !
b101011 3
b100111110011 #
b100111110011 /
b101011 1
b100111110011 4
b11111111111111111111100101101100 0
b111100 2
b101101000100 5
b10010110000 (
b10010110000 -
1*
1&
b10010110000 6
#490000
0&
#495000
b11101 !
b11101 3
b100100001000 #
b100100001000 /
b11101 1
b100100001000 4
b11111111111111111111101010010010 0
b101011 2
b101000011110 5
1&
#500000
0&
#505000
0"
0*
1&
#510000
0&
#515000
1&
#520000
0&
#525000
1"
b10010 !
b10010 3
b100001010100 #
b100001010100 /
b10010 1
b100001010100 4
b11111111111111111111101111101111 0
b11101 2
b100100100101 5
b10100010100 (
b10100010100 -
1*
1&
b10100010100 6
#530000
0&
#535000
b1001 !
b1001 3
b11110111100 #
b11110111100 /
b1001 1
b11110111100 4
b11111111111111111111110010101110 0
b10010 2
b100001100110 5
1&
#540000
0&
#545000
0"
0*
1&
#550000
0&
#555000
1&
#560000
0&
#565000
1"
b11 !
b11 3
b11101001111 #
b11101001111 /
b11 1
b11101001111 4
b11111111111111111111110110110011 0
b1001 2
b11111000101 5
b10101111000 (
b10101111000 -
1*
1&
b10101111000 6
#570000
0&
#575000
b1111111111111110 !
b1111111111111110 3
b11011110011 #
b11011110011 /
b11111111111111111111111111111110 1
b11011110011 4
b11111111111111111111111000100110 0
b11 2
b11101010010 5
1&
#580000
0&
#585000
0"
0*
1&
#590000
0&
#595000
1&
#600000
0&
#605000
1"
b1111111111111011 !
b1111111111111011 3
b11010111001 #
b11010111001 /
b11111111111111111111111111111011 1
b11010111001 4
b11111111111111111111111011101011 0
b11111111111111111111111111111110 2
b11011110001 5
b10111011100 (
b10111011100 -
1*
1&
b10111011100 6
#610000
0&
#615000
b1111111111111000 !
b1111111111111000 3
b11010001000 #
b11010001000 /
b11111111111111111111111111111000 1
b11010001000 4
b11111111111111111111111100101000 0
b11111111111111111111111111111011 2
b11010110100 5
1&
#620000
0&
#625000
0"
0*
1&
#630000
0&
#635000
1&
#640000
0&
#645000
1"
b1111111111110111 !
b1111111111110111 3
b11001110011 #
b11001110011 /
b11111111111111111111111111110111 1
b11001110011 4
b11111111111111111111111111000000 0
b11111111111111111111111111111000 2
b11010000000 5
b11001000000 (
b11001000000 -
1*
1&
b11001000000 6
#650000
0&
#655000
b1111111111110110 !
b1111111111110110 3
b11001100001 #
b11001100001 /
b11111111111111111111111111110110 1
b11001100001 4
b11111111111111111111111111010110 0
b11111111111111111111111111110111 2
b11001101010 5
1&
#660000
0&
#665000
0"
0*
1&
