boreal bci 2/boreal_neuro_core_v2.4/rtl/boreal_lms_decoder.v
/*
 * Boreal BCI Least Mean Squares (LMS) Adaptive Decoder
 * 
 * Purpose:
 * Dynamically updates its internal decoding weights on a cycle-by-cycle basis
 * to minimize the residual error signal. Compensates for biological signal drift
 * and neuroplasticity in real-time.
 * 
 * Architecture:
 * 1D Linear Adaptive Combiner
 * Inputs:  N spatial components (e.g., from CSP filter/Kalman)
 * Outputs: 1 Decoded state value
 * 
 * Equation (Standard LMS):
 * y(n) = w(n) * x(n) 
 * e(n) = d(n) - y(n)   [d(n) is the desired target/error feedback]
 * w(n+1) = w(n) + 2 * mu * e(n) * x(n)
 * 
 * Note: Fixed-point Q1.15 arithmetic implies `mu` is a bit logical right-shift
 * (Division by powers of 2) for maximum DSP slice throughput.
 */

module boreal_lms_decoder #(
    parameter NUM_COMPONENTS = 4,

    // Learning Rate (mu). Implemented as a right bit shift.
    // E.g., MU_SHIFT = 8 -> mu = 1/256 ≈ 0.0039
    // A smaller mu prevents weight explosion (divergence) from biological spikes.
    parameter MU_SHIFT = 10 
)(
    input  wire        clk,
    input  wire        rst_n,
    input  wire        enable,
    input  wire        valid_in,

    // Inputs (from Kalman/CSP)
    input  wire signed [15:0] comp_in_0,
    input  wire signed [15:0] comp_in_1,
    input  wire signed [15:0] comp_in_2,
    input  wire signed [15:0] comp_in_3,

    // Error Feedback (e.g., Target Pos - Current Pos)
    // Positive error = output needs to be more positive
    input  wire signed [15:0] error_in,

    // Adaptive Output
    output reg signed [15:0]  state_out,
    output reg                valid_out
);

    // Q1.15 Fixed Point Scaling
    localparam FP_SHIFT = 15;

    // Weight Registers (Dynamic)
    reg signed [15:0] w_0;
    reg signed [15:0] w_1;
    reg signed [15:0] w_2;
    reg signed [15:0] w_3;

    // Combinatorial Multiplier Pipelines (Stage 1: Output Calculation)
    reg signed [31:0] mul_x0, mul_x1, mul_x2, mul_x3;
    reg signed [31:0] sum_x;
    
    // Combinatorial Multiplier Pipelines (Stage 2: Weight Update 'Delta')
    reg signed [31:0] dw_0, dw_1, dw_2, dw_3;

    always @(posedge clk or negedge rst_n) begin
        if (!rst_n) begin
            // Reset weights to a neutral or slight positive initial prior
            w_0 <= 16'h0000;
            w_1 <= 16'h0000;
            w_2 <= 16'h0000;
            w_3 <= 16'h0000;
            
            state_out <= 0;
            valid_out <= 0;
        end else if (enable) begin
            if (valid_in) begin
                
                // ------------------------------------------------------------
                // 1. Output Calculation (y(n) = W * X)
                // ------------------------------------------------------------
                // Must pad to 32-bits BEFORE multiplying to prevent intermediate 16-bit overflow
                mul_x0 = $signed({{16{w_0[15]}}, w_0}) * $signed({{16{comp_in_0[15]}}, comp_in_0});
                mul_x1 = $signed({{16{w_1[15]}}, w_1}) * $signed({{16{comp_in_1[15]}}, comp_in_1});
                mul_x2 = $signed({{16{w_2[15]}}, w_2}) * $signed({{16{comp_in_2[15]}}, comp_in_2});
                mul_x3 = $signed({{16{w_3[15]}}, w_3}) * $signed({{16{comp_in_3[15]}}, comp_in_3});

                sum_x = (mul_x0 >>> FP_SHIFT) + (mul_x1 >>> FP_SHIFT) + 
                        (mul_x2 >>> FP_SHIFT) + (mul_x3 >>> FP_SHIFT);

                // Saturation arithmetic guard for output
                if (sum_x > 32767) state_out <= 32767;
                else if (sum_x < -32768) state_out <= -32768;
                else state_out <= sum_x[15:0];

                // ------------------------------------------------------------
                // 2. Weight Update (w_new = w_old + (mu * e * x))
                // ------------------------------------------------------------
                
                // Calculate weight deltas based on backpropagated error
                // The 2* factor from standard LMS is absorbed into the mu_shift.
                // Shift by FP_SHIFT removes the fixed-point Q1.15 multiplication overhead.
                // Shift by MU_SHIFT applies the learning rate scalar.
                dw_0 = ($signed({{16{error_in[15]}}, error_in}) * $signed({{16{comp_in_0[15]}}, comp_in_0})) >>> (FP_SHIFT + MU_SHIFT);
                dw_1 = ($signed({{16{error_in[15]}}, error_in}) * $signed({{16{comp_in_1[15]}}, comp_in_1})) >>> (FP_SHIFT + MU_SHIFT);
                dw_2 = ($signed({{16{error_in[15]}}, error_in}) * $signed({{16{comp_in_2[15]}}, comp_in_2})) >>> (FP_SHIFT + MU_SHIFT);
                dw_3 = ($signed({{16{error_in[15]}}, error_in}) * $signed({{16{comp_in_3[15]}}, comp_in_3})) >>> (FP_SHIFT + MU_SHIFT);

                // Update physical registers with saturation
                // To prevent DSP runaway upon noisy disconnected electrodes, clip weights
                
                if (w_0 + dw_0 > 32767) w_0 <= 32767;
                else if (w_0 + dw_0 < -32768) w_0 <= -32768;
                else w_0 <= w_0 + dw_0[15:0];

                if (w_1 + dw_1 > 32767) w_1 <= 32767;
                else if (w_1 + dw_1 < -32768) w_1 <= -32768;
                else w_1 <= w_1 + dw_1[15:0];

                if (w_2 + dw_2 > 32767) w_2 <= 32767;
                else if (w_2 + dw_2 < -32768) w_2 <= -32768;
                else w_2 <= w_2 + dw_2[15:0];

                if (w_3 + dw_3 > 32767) w_3 <= 32767;
                else if (w_3 + dw_3 < -32768) w_3 <= -32768;
                else w_3 <= w_3 + dw_3[15:0];

                valid_out <= 1;
            end else begin
                valid_out <= 0;
            end
        end else begin
            valid_out <= 0;
        end
    end

endmodule

boreal bci 2/boreal_neuro_core_v2.4/sim/tb_boreal_lms_decoder.v
`timescale 1ns / 1ps

module tb_boreal_lms_decoder;

    // Inputs
    reg clk;
    reg rst_n;
    reg enable;
    reg valid_in;
    reg signed [15:0] comp_in_0;
    reg signed [15:0] comp_in_1;
    reg signed [15:0] comp_in_2;
    reg signed [15:0] comp_in_3;
    reg signed [15:0] error_in;

    // Outputs
    wire signed [15:0] state_out;
    wire valid_out;

    // Instantiate UUT
    // Using MU_SHIFT = 4 for faster convergence during short simulation
    // mu = 1/16 = 0.0625
    boreal_lms_decoder #(
        .NUM_COMPONENTS(4),
        .MU_SHIFT(4) 
    ) uut (
        .clk(clk),
        .rst_n(rst_n),
        .enable(enable),
        .valid_in(valid_in),
        .comp_in_0(comp_in_0),
        .comp_in_1(comp_in_1),
        .comp_in_2(comp_in_2),
        .comp_in_3(comp_in_3),
        .error_in(error_in),
        .state_out(state_out),
        .valid_out(valid_out)
    );

    // Clock generator (100MHz)
    always #5 clk = ~clk;

    // Helper task to apply an inference cycle
    task apply_inference;
        input signed [15:0] c0, c1, c2, c3;
        input signed [15:0] err;
        begin
            @(posedge clk);
            valid_in = 1;
            comp_in_0 = c0;
            comp_in_1 = c1;
            comp_in_2 = c2;
            comp_in_3 = c3;
            error_in  = err;
            
            @(posedge clk);
            valid_in = 0;
            
            #50; // Allow pipelined state and weight registers to update
        end
    endtask

    integer i;

    initial begin
        // Reset Inputs
        clk = 0;
        rst_n = 0;
        enable = 0;
        valid_in = 0;
        comp_in_0 = 0;
        comp_in_1 = 0;
        comp_in_2 = 0;
        comp_in_3 = 0;
        error_in = 0;

        $dumpfile("sim/boreal_lms.vcd");
        $dumpvars(0, tb_boreal_lms_decoder);

        // Wait for global reset
        #100;
        rst_n = 1;
        #20;
        enable = 1;

        $display("=== BOREAL LMS DECODER SIMULATION ===");

        // ---------------------------------------------------------
        // Test 1: Positive Error Feedback
        // Objective: Inject a constant positive signal and a positive error
        // Expected: The weights should grow positively, pushing state_out higher over time 
        // ---------------------------------------------------------
        $display("--- Test 1: Positive Adaptation ---");
        
        $display("Initial State (W=0)  -> Out: %d | (Expecting ~ 0)", state_out);
        
        // Loop 10 times to watch the weights adapt
        for (i = 0; i < 15; i = i + 1) begin
            apply_inference(10000, 10000, 10000, 10000, 5000);
            $display("Adapt %0d -> Out: %d", i, state_out);
        end


        // ---------------------------------------------------------
        // Test 2: Negative Error Feedback (Reversal)
        // Objective: Reverse the error signal to negative
        // Expected: The weights should begin shrinking, driving state_out down
        // ---------------------------------------------------------
        $display("--- Test 2: Negative Adaptation Reversal ---");
        
        // Loop 10 times with negative error
        for (i = 0; i < 15; i = i + 1) begin
            apply_inference(10000, 10000, 10000, 10000, -5000);
            $display("Adapt %0d -> Out: %d", i, state_out);
        end

        // ---------------------------------------------------------
        // Test 3: Convergence (Zero Error)
        // Objective: Set error to zero.
        // Expected: The weights lock in place and state_out remains stable
        // ---------------------------------------------------------
        $display("--- Test 3: Stable Convergence ---");
        apply_inference(10000, 10000, 10000, 10000, 0);
        $display("Stable 1 -> Out: %d", state_out);
        apply_inference(10000, 10000, 10000, 10000, 0);
        $display("Stable 2 -> Out: %d", state_out);
        apply_inference(1000, 1000, 1000, 1000, 0);
        $display("Stable 3 -> Out: %d", state_out);


        $display("=== SIMULATION COMPLETE ===");
        $finish;
    end

endmodule

boreal bci 2/boreal_neuro_core_v2.4/sim/boreal_lms.vcd
$date
	Tue Feb 24 14:41:33 2026
$end
$version
	Icarus Verilog
$end
$timescale
	1ps
$end
$scope module tb_boreal_lms_decoder $end
$var wire 1 ! valid_out $end
$var wire 16 " state_out [15:0] $end
$var reg 1 # clk $end
$var reg 16 $ comp_in_0 [15:0] $end
$var reg 16 % comp_in_1 [15:0] $end
$var reg 16 & comp_in_2 [15:0] $end
$var reg 16 ' comp_in_3 [15:0] $end
$var reg 1 ( enable $end
$var reg 16 ) error_in [15:0] $end
$var reg 1 * rst_n $end
$var reg 1 + valid_in $end
$var integer 32 , i [31:0] $end
$scope module uut $end
$var wire 1 # clk $end
$var wire 16 - comp_in_0 [15:0] $end
$var wire 16 . comp_in_1 [15:0] $end
$var wire 16 / comp_in_2 [15:0] $end
$var wire 16 0 comp_in_3 [15:0] $end
$var wire 1 ( enable $end
$var wire 16 1 error_in [15:0] $end
$var wire 1 * rst_n $end
$var wire 1 + valid_in $end
$var parameter 32 2 FP_SHIFT $end
$var parameter 32 3 MU_SHIFT $end
$var parameter 32 4 NUM_COMPONENTS $end
$var reg 32 5 dw_0 [31:0] $end
$var reg 32 6 dw_1 [31:0] $end
$var reg 32 7 dw_2 [31:0] $end
$var reg 32 8 dw_3 [31:0] $end
$var reg 32 9 mul_x0 [31:0] $end
$var reg 32 : mul_x1 [31:0] $end
$var reg 32 ; mul_x2 [31:0] $end
$var reg 32 < mul_x3 [31:0] $end
$var reg 16 = state_out [15:0] $end
$var reg 32 > sum_x [31:0] $end
$var reg 1 ! valid_out $end
$var reg 16 ? w_0 [15:0] $end
$var reg 16 @ w_1 [15:0] $end
$var reg 16 A w_2 [15:0] $end
$var reg 16 B w_3 [15:0] $end
$upscope $end
$scope task apply_inference $end
$var reg 16 C c0 [15:0] $end
$var reg 16 D c1 [15:0] $end
$var reg 16 E c2 [15:0] $end
$var reg 16 F c3 [15:0] $end
$var reg 16 G err [15:0] $end
$upscope $end
$upscope $end
$enddefinitions $end
$comment Show the parameter values. $end
$dumpall
b100 4
b100 3
b1111 2
$end
#0
$dumpvars
bx G
bx F
bx E
bx D
bx C
b0 B
b0 A
b0 @
b0 ?
bx >
b0 =
bx <
bx ;
bx :
bx 9
bx 8
bx 7
bx 6
bx 5
b0 1
b0 0
b0 /
b0 .
b0 -
bx ,
0+
0*
b0 )
0(
b0 '
b0 &
b0 %
b0 $
0#
b0 "
0!
$end
#5000
1#
#10000
0#
#15000
1#
#20000
0#
#25000
1#
#30000
0#
#35000
1#
#40000
0#
#45000
1#
#50000
0#
#55000
1#
#60000
0#
#65000
1#
#70000
0#
#75000
1#
#80000
0#
#85000
1#
#90000
0#
#95000
1#
#100000
0#
1*
#105000
1#
#110000
0#
#115000
1#
#120000
0#
b1001110001000 G
b10011100010000 F
b10011100010000 E
b10011100010000 D
b10011100010000 C
b0 ,
1(
#125000
1!
b1011111 B
b1011111 A
b1011111 @
b1011111 ?
b1011111 8
b1011111 7
b1011111 6
b1011111 5
b0 >
b0 <
b0 ;
b0 :
b0 9
b1001110001000 )
b1001110001000 1
b10011100010000 '
b10011100010000 0
b10011100010000 &
b10011100010000 /
b10011100010000 %
b10011100010000 .
b10011100010000 $
b10011100010000 -
1+
1#
#130000
0#
#135000
0!
0+
1#
#140000
0#
#145000
1#
#150000
0#
#155000
1#
#160000
0#
#165000
1#
#170000
0#
#175000
1#
#180000
0#
#185000
1!
b10111110 B
b10111110 A
b10111110 @
b10111110 ?
b1110000 "
b1110000 =
b1110000 >
b11100111111011110000 <
b11100111111011110000 ;
b11100111111011110000 :
b11100111111011110000 9
1+
1#
b1 ,
#190000
0#
#195000
0!
0+
1#
#200000
0#
#205000
1#
#210000
0#
#215000
1#
#220000
0#
#225000
1#
#230000
0#
#235000
1#
#240000
0#
#245000
1!
b100011101 B
b100011101 A
b100011101 @
b100011101 ?
b11100100 "
b11100100 =
b11100100 >
b111001111110111100000 <
b111001111110111100000 ;
b111001111110111100000 :
b111001111110111100000 9
1+
1#
b10 ,
#250000
0#
#255000
0!
0+
1#
#260000
0#
#265000
1#
#270000
0#
#275000
1#
#280000
0#
#285000
1#
#290000
0#
#295000
1#
#300000
0#
#305000
1!
b101111100 B
b101111100 A
b101111100 @
b101111100 ?
b101011000 "
b101011000 =
b101011000 >
b1010110111110011010000 <
b1010110111110011010000 ;
b1010110111110011010000 :
b1010110111110011010000 9
1+
1#
b11 ,
#310000
0#
#315000
0!
0+
1#
#320000
0#
#325000
1#
#330000
0#
#335000
1#
#340000
0#
#345000
1#
#350000
0#
#355000
1#
#360000
0#
#365000
1!
b111011011 B
b111011011 A
b111011011 @
b111011011 ?
b111001100 "
b111001100 =
b111001100 >
b1110011111101111000000 <
b1110011111101111000000 ;
b1110011111101111000000 :
b1110011111101111000000 9
1+
1#
b100 ,
#370000
0#
#375000
0!
0+
1#
#380000
0#
#385000
1#
#390000
0#
#395000
1#
#400000
0#
#405000
1#
#410000
0#
#415000
1#
#420000
0#
#425000
1!
b1000111010 B
b1000111010 A
b1000111010 @
b1000111010 ?
b1001000000 "
b1001000000 =
b1001000000 >
b10010000111101010110000 <
b10010000111101010110000 ;
b10010000111101010110000 :
b10010000111101010110000 9
1+
1#
b101 ,
#430000
0#
#435000
0!
0+
1#
#440000
0#
#445000
1#
#450000
0#
#455000
1#
#460000
0#
#465000
1#
#470000
0#
#475000
1#
#480000
0#
#485000
1!
b1010011001 B
b1010011001 A
b1010011001 @
b1010011001 ?
b1010110100 "
b1010110100 =
b1010110100 >
b10101101111100110100000 <
b10101101111100110100000 ;
b10101101111100110100000 :
b10101101111100110100000 9
1+
1#
b110 ,
#490000
0#
#495000
0!
0+
1#
#500000
0#
#505000
1#
#510000
0#
#515000
1#
#520000
0#
#525000
1#
#530000
0#
#535000
1#
#540000
0#
#545000
1!
b1011111000 B
b1011111000 A
b1011111000 @
b1011111000 ?
b1100101000 "
b1100101000 =
b1100101000 >
b11001010111100010010000 <
b11001010111100010010000 ;
b11001010111100010010000 :
b11001010111100010010000 9
1+
1#
b111 ,
#550000
0#
#555000
0!
0+
1#
#560000
0#
#565000
1#
#570000
0#
#575000
1#
#580000
0#
#585000
1#
#590000
0#
#595000
1#
#600000
0#
#605000
1!
b1101010111 B
b1101010111 A
b1101010111 @
b1101010111 ?
b1110011100 "
b1110011100 =
b1110011100 >
b11100111111011110000000 <
b11100111111011110000000 ;
b11100111111011110000000 :
b11100111111011110000000 9
1+
1#
b1000 ,
#610000
0#
#615000
0!
0+
1#
#620000
0#
#625000
1#
#630000
0#
#635000
1#
#640000
0#
#645000
1#
#650000
0#
#655000
1#
#660000
0#
#665000
1!
b1110110110 B
b1110110110 A
b1110110110 @
b1110110110 ?
b10000010000 "
b10000010000 =
b10000010000 >
b100000100111011001110000 <
b100000100111011001110000 ;
b100000100111011001110000 :
b100000100111011001110000 9
1+
1#
b1001 ,
#670000
0#
#675000
0!
0+
1#
#680000
0#
#685000
1#
#690000
0#
#695000
1#
#700000
0#
#705000
1#
#710000
0#
#715000
1#
#720000
0#
#725000
1!
b10000010101 B
b10000010101 A
b10000010101 @
b10000010101 ?
b10010000100 "
b10010000100 =
b10010000100 >
b100100001111010101100000 <
b100100001111010101100000 ;
b100100001111010101100000 :
b100100001111010101100000 9
1+
1#
b1010 ,
#730000
0#
#735000
0!
0+
1#
#740000
0#
#745000
1#
#750000
0#
#755000
1#
#760000
0#
#765000
1#
#770000
0#
#775000
1#
#780000
0#
#785000
1!
b10001110100 B
b10001110100 A
b10001110100 @
b10001110100 ?
b10011111000 "
b10011111000 =
b10011111000 >
b100111110111010001010000 <
b100111110111010001010000 ;
b100111110111010001010000 :
b100111110111010001010000 9
1+
1#
b1011 ,
#790000
0#
#795000
0!
0+
1#
#800000
0#
#805000
1#
#810000
0#
#815000
1#
#820000
0#
#825000
1#
#830000
0#
#835000
1#
#840000
0#
#845000
1!
b10011010011 B
b10011010011 A
b10011010011 @
b10011010011 ?
b10101101100 "
b10101101100 =
b10101101100 >
b101011011111001101000000 <
b101011011111001101000000 ;
b101011011111001101000000 :
b101011011111001101000000 9
1+
1#
b1100 ,
#850000
0#
#855000
0!
0+
1#
#860000
0#
#865000
1#
#870000
0#
#875000
1#
#880000
0#
#885000
1#
#890000
0#
#895000
1#
#900000
0#
#905000
1!
b10100110010 B
b10100110010 A
b10100110010 @
b10100110010 ?
b10111100000 "
b10111100000 =
b10111100000 >
b101111000111001000110000 <
b101111000111001000110000 ;
b101111000111001000110000 :
b101111000111001000110000 9
1+
1#
b1101 ,
#910000
0#
#915000
0!
0+
1#
#920000
0#
#925000
1#
#930000
0#
#935000
1#
#940000
0#
#945000
1#
#950000
0#
#955000
1#
#960000
0#
#965000
1!
b10110010001 B
b10110010001 A
b10110010001 @
b10110010001 ?
b11001010100 "
b11001010100 =
b11001010100 >
b110010101111000100100000 <
b110010101111000100100000 ;
b110010101111000100100000 :
b110010101111000100100000 9
1+
1#
b1110 ,
#970000
0#
#975000
0!
0+
1#
#980000
0#
#985000
1#
#990000
0#
#995000
1#
#1000000
0#
#1005000
1#
#1010000
0#
#1015000
1#
#1020000
0#
#1025000
1!
b10100110001 B
b10100110001 A
b10100110001 @
b10100110001 ?
b11011001000 "
b11011001000 =
b11111111111111111111111110100000 8
b11111111111111111111111110100000 7
b11111111111111111111111110100000 6
b11111111111111111111111110100000 5
b11011001000 >
b110110010111000000010000 <
b110110010111000000010000 ;
b110110010111000000010000 :
b110110010111000000010000 9
b1110110001111000 )
b1110110001111000 1
1+
1#
b1110110001111000 G
b0 ,
#1030000
0#
#1035000
0!
0+
1#
#1040000
0#
#1045000
1#
#1050000
0#
#1055000
1#
#1060000
0#
#1065000
1#
#1070000
0#
#1075000
1#
#1080000
0#
#1085000
1!
b10011010001 B
b10011010001 A
b10011010001 @
b10011010001 ?
b11001010100 "
b11001010100 =
b11001010100 >
b110010101100101000010000 <
b110010101100101000010000 ;
b110010101100101000010000 :
b110010101100101000010000 9
1+
1#
b1 ,
#1090000
0#
#1095000
0!
0+
1#
#1100000
0#
#1105000
1#
#1110000
0#
#1115000
1#
#1120000
0#
#1125000
1#
#1130000
0#
#1135000
1#
#1140000
0#
#1145000
1!
b10001110001 B
b10001110001 A
b10001110001 @
b10001110001 ?
b10111100000 "
b10111100000 =
b10111100000 >
b101111000010010000010000 <
b101111000010010000010000 ;
b101111000010010000010000 :
b101111000010010000010000 9
1+
1#
b10 ,
#1150000
0#
#1155000
0!
0+
1#
#1160000
0#
#1165000
1#
#1170000
0#
#1175000
1#
#1180000
0#
#1185000
1#
#1190000
0#
#1195000
1#
#1200000
0#
#1205000
1!
b10000010001 B
b10000010001 A
b10000010001 @
b10000010001 ?
b10101101000 "
b10101101000 =
b10101101000 >
b101011010111111000010000 <
b101011010111111000010000 ;
b101011010111111000010000 :
b101011010111111000010000 9
1+
1#
b11 ,
#1210000
0#
#1215000
0!
0+
1#
#1220000
0#
#1225000
1#
#1230000
0#
#1235000
1#
#1240000
0#
#1245000
1#
#1250000
0#
#1255000
1#
#1260000
0#
#1265000
1!
b1110110001 B
b1110110001 A
b1110110001 @
b1110110001 ?
b10011110100 "
b10011110100 =
b10011110100 >
b100111101101100000010000 <
b100111101101100000010000 ;
b100111101101100000010000 :
b100111101101100000010000 9
1+
1#
b100 ,
#1270000
0#
#1275000
0!
0+
1#
#1280000
0#
#1285000
1#
#1290000
0#
#1295000
1#
#1300000
0#
#1305000
1#
#1310000
0#
#1315000
1#
#1320000
0#
#1325000
1!
b1101010001 B
b1101010001 A
b1101010001 @
b1101010001 ?
b10010000000 "
b10010000000 =
b10010000000 >
b100100000011001000010000 <
b100100000011001000010000 ;
b100100000011001000010000 :
b100100000011001000010000 9
1+
1#
b101 ,
#1330000
0#
#1335000
0!
0+
1#
#1340000
0#
#1345000
1#
#1350000
0#
#1355000
1#
#1360000
0#
#1365000
1#
#1370000
0#
#1375000
1#
#1380000
0#
#1385000
1!
b1011110001 B
b1011110001 A
b1011110001 @
b1011110001 ?
b10000001100 "
b10000001100 =
b10000001100 >
b100000011000110000010000 <
b100000011000110000010000 ;
b100000011000110000010000 :
b100000011000110000010000 9
1+
1#
b110 ,
#1390000
0#
#1395000
0!
0+
1#
#1400000
0#
#1405000
1#
#1410000
0#
#1415000
1#
#1420000
0#
#1425000
1#
#1430000
0#
#1435000
1#
#1440000
0#
#1445000
1!
b1010010001 B
b1010010001 A
b1010010001 @
b1010010001 ?
b1110010100 "
b1110010100 =
b1110010100 >
b11100101110011000010000 <
b11100101110011000010000 ;
b11100101110011000010000 :
b11100101110011000010000 9
1+
1#
b111 ,
#1450000
0#
#1455000
0!
0+
1#
#1460000
0#
#1465000
1#
#1470000
0#
#1475000
1#
#1480000
0#
#1485000
1#
#1490000
0#
#1495000
1#
#1500000
0#
#1505000
1!
b1000110001 B
b1000110001 A
b1000110001 @
b1000110001 ?
b1100100000 "
b1100100000 =
b1100100000 >
b11001000100000000010000 <
b11001000100000000010000 ;
b11001000100000000010000 :
b11001000100000000010000 9
1+
1#
b1000 ,
#1510000
0#
#1515000
0!
0+
1#
#1520000
0#
#1525000
1#
#1530000
0#
#1535000
1#
#1540000
0#
#1545000
1#
#1550000
0#
#1555000
1#
#1560000
0#
#1565000
1!
b111010001 B
b111010001 A
b111010001 @
b111010001 ?
b1010101100 "
b1010101100 =
b1010101100 >
b10101011001101000010000 <
b10101011001101000010000 ;
b10101011001101000010000 :
b10101011001101000010000 9
1+
1#
b1001 ,
#1570000
0#
#1575000
0!
0+
1#
#1580000
0#
#1585000
1#
#1590000
0#
#1595000
1#
#1600000
0#
#1605000
1#
#1610000
0#
#1615000
1#
#1620000
0#
#1625000
1!
b101110001 B
b101110001 A
b101110001 @
b101110001 ?
b1000110100 "
b1000110100 =
b1000110100 >
b10001101111010000010000 <
b10001101111010000010000 ;
b10001101111010000010000 :
b10001101111010000010000 9
1+
1#
b1010 ,
#1630000
0#
#1635000
0!
0+
1#
#1640000
0#
#1645000
1#
#1650000
0#
#1655000
1#
#1660000
0#
#1665000
1#
#1670000
0#
#1675000
1#
#1680000
0#
#1685000
1!
b100010001 B
b100010001 A
b100010001 @
b100010001 ?
b111000000 "
b111000000 =
b111000000 >
b1110000100111000010000 <
b1110000100111000010000 ;
b1110000100111000010000 :
b1110000100111000010000 9
1+
1#
b1011 ,
#1690000
0#
#1695000
0!
0+
1#
#1700000
0#
#1705000
1#
#1710000
0#
#1715000
1#
#1720000
0#
#1725000
1#
#1730000
0#
#1735000
1#
#1740000
0#
#1745000
1!
b10110001 B
b10110001 A
b10110001 @
b10110001 ?
b101001100 "
b101001100 =
b101001100 >
b1010011010100000010000 <
b1010011010100000010000 ;
b1010011010100000010000 :
b1010011010100000010000 9
1+
1#
b1100 ,
#1750000
0#
#1755000
0!
0+
1#
#1760000
0#
#1765000
1#
#1770000
0#
#1775000
1#
#1780000
0#
#1785000
1#
#1790000
0#
#1795000
1#
#1800000
0#
#1805000
1!
b1010001 B
b1010001 A
b1010001 @
b1010001 ?
b11011000 "
b11011000 =
b11011000 >
b110110000001000010000 <
b110110000001000010000 ;
b110110000001000010000 :
b110110000001000010000 9
1+
1#
b1101 ,
#1810000
0#
#1815000
0!
0+
1#
#1820000
0#
#1825000
1#
#1830000
0#
#1835000
1#
#1840000
0#
#1845000
1#
#1850000
0#
#1855000
1#
#1860000
0#
#1865000
1!
b1111111111110001 B
b1111111111110001 A
b1111111111110001 @
b1111111111110001 ?
b1100000 "
b1100000 =
b1100000 >
b11000101110000010000 <
b11000101110000010000 ;
b11000101110000010000 :
b11000101110000010000 9
1+
1#
b1110 ,
#1870000
0#
#1875000
0!
0+
1#
#1880000
0#
#1885000
1#
#1890000
0#
#1895000
1#
#1900000
0#
#1905000
1#
#1910000
0#
#1915000
1#
#1920000
0#
#1925000
1!
b1111111111101100 "
b1111111111101100 =
b0 8
b0 7
b0 6
b0 5
b11111111111111111111111111101100 >
b11111111111111011011011000010000 <
b11111111111111011011011000010000 ;
b11111111111111011011011000010000 :
b11111111111111011011011000010000 9
b0 )
b0 1
1+
1#
b0 G
b1111 ,
#1930000
0#
#1935000
0!
0+
1#
#1940000
0#
#1945000
1#
#1950000
0#
#1955000
1#
#1960000
0#
#1965000
1#
#1970000
0#
#1975000
1#
#1980000
0#
#1985000
1!
1+
1#
#1990000
0#
#1995000
0!
0+
1#
#2000000
0#
#2005000
1#
#2010000
0#
#2015000
1#
#2020000
0#
#2025000
1#
#2030000
0#
#2035000
1#
#2040000
0#
#2045000
1!
b1111111111111100 "
b1111111111111100 =
b11111111111111111111111111111100 >
b11111111111111111100010101101000 <
b11111111111111111100010101101000 ;
b11111111111111111100010101101000 :
b11111111111111111100010101101000 9
b1111101000 '
b1111101000 0
b1111101000 &
b1111101000 /
b1111101000 %
b1111101000 .
b1111101000 $
b1111101000 -
1+
1#
b1111101000 F
b1111101000 E
b1111101000 D
b1111101000 C
#2050000
0#
#2055000
0!
0+
1#
