boreal bci 2/boreal_neuro_core_v2.4/rtl/boreal_symbolic_mapper.v
/*
 * Boreal BCI Symbolic Intent Mapper
 * 
 * Purpose:
 * Converts continuous, continuous 2D BCI cursor vectors into discrete, debounced
 * symbolic triggers (e.g., D-Pad, actions) via a "stare-to-select" temporal integration.
 * Prevents accidental neurological misfires from triggering system actions.
 */

module boreal_symbolic_mapper #(
    // Constants for Thresholds (16-bit Signed Space: -32768 to 32767)
    // We arbitrarily set boundaries at +/- 10000 
    parameter signed [15:0] THRESHOLD_POS = 16'd10000,
    parameter signed [15:0] THRESHOLD_NEG = -16'd10000,
    
    // Dwell Time: The number of consecutive inference cycles the vector must be 
    // held past the threshold to confirm selection.
    // 10 cycles ≈ small 0.1s lag assuming 100Hz BCI refresh rate
    parameter DWELL_TIME_CYCLES = 10,

    // Refractory Period: The number of cycles the system ignores ALL inputs 
    // after dropping a trigger pulse, preventing bouncing.
    parameter COOLDOWN_CYCLES = 50
)(
    input  wire        clk,
    input  wire        rst_n,
    input  wire        enable,
    input  wire        valid_in,

    // Continuous smooth vector inputs (from Boreal Active Inference)
    input  wire signed [15:0] cursor_x,
    input  wire signed [15:0] cursor_y,

    // Discrete 4-Bit Output Trigger Vector: [UP, DOWN, LEFT, RIGHT]
    // Asserted HIGH for a SINGLE clock cycle upon successful integration
    output reg [3:0]   symbol_trigger,
    output reg         valid_out
);

    // Internal Register State Machines
    reg [15:0] dwell_counter;
    reg [15:0] cooldown_counter;
    reg [2:0]  state;

    // States
    localparam STATE_IDLE      = 3'b000;
    localparam STATE_INTEGRATE = 3'b001;
    localparam STATE_TRIGGER   = 3'b010;
    localparam STATE_COOLDOWN  = 3'b011;

    // Internal boundary flags (combinatorial limits)
    wire cross_right = (cursor_x >= THRESHOLD_POS);
    wire cross_left  = (cursor_x <= THRESHOLD_NEG);
    wire cross_up    = (cursor_y >= THRESHOLD_POS);
    wire cross_down  = (cursor_y <= THRESHOLD_NEG);

    // Identify which discrete symbol is currently the "target" being stared at
    // Only one symbol is allowed at a time (cardinal directions only)
    reg [3:0] active_target;

    always @(posedge clk or negedge rst_n) begin
        if (!rst_n) begin
            dwell_counter <= 0;
            cooldown_counter <= 0;
            state <= STATE_IDLE;
            active_target <= 4'b0000;
            symbol_trigger <= 4'b0000;
            valid_out <= 0;
        end else if (enable) begin
            
            // Generate clean 1-cycle trigger pulses
            symbol_trigger <= 4'b0000; 
            valid_out <= 0;

            if (valid_in) begin
                case (state)
                    STATE_IDLE: begin
                        // Check if cursor crossed any cardinal boundary
                        if (cross_up)    active_target <= 4'b1000;
                        else if (cross_down)  active_target <= 4'b0100;
                        else if (cross_left)  active_target <= 4'b0010;
                        else if (cross_right) active_target <= 4'b0001;
                        else active_target <= 4'b0000;

                        if (active_target != 4'b0000) begin
                            dwell_counter <= 1;
                            state <= STATE_INTEGRATE;
                        end
                    end

                    STATE_INTEGRATE: begin
                        // Check if the user is maintaining the SPECIFIC intent
                        if (
                            (active_target == 4'b1000 && cross_up)    ||
                            (active_target == 4'b0100 && cross_down)  ||
                            (active_target == 4'b0010 && cross_left)  ||
                            (active_target == 4'b0001 && cross_right)
                        ) begin
                            // Maintain intent, increment dwell integration
                            // Emit trigger immediately when dwell threshold is reached
                            if (dwell_counter >= (DWELL_TIME_CYCLES - 1)) begin
                                symbol_trigger <= active_target;
                                valid_out <= 1;
                                cooldown_counter <= 0;
                                state <= STATE_COOLDOWN;
                            end else begin
                                dwell_counter <= dwell_counter + 1;
                            end
                        end else begin
                            // User slipped off the boundary, intent lost
                            active_target <= 4'b0000;
                            dwell_counter <= 0;
                            state <= STATE_IDLE;
                        end
                    end

                    STATE_COOLDOWN: begin
                        // Ignore all crossing logic until refractory period ends
                        if (cooldown_counter >= COOLDOWN_CYCLES) begin
                            state <= STATE_IDLE;
                            active_target <= 4'b0000;
                        end else begin
                            cooldown_counter <= cooldown_counter + 1;
                        end
                    end

                    default: state <= STATE_IDLE;
                endcase
            end
        end else begin
            symbol_trigger <= 4'b0000;
            valid_out <= 0;
        end
    end

endmodule

boreal bci 2/boreal_neuro_core_v2.4/sim/tb_boreal_symbolic_mapper.v
`timescale 1ns / 1ps

module tb_boreal_symbolic_mapper;

    // Inputs
    reg clk;
    reg rst_n;
    reg enable;
    reg valid_in;
    reg signed [15:0] cursor_x;
    reg signed [15:0] cursor_y;

    // Outputs
    wire [3:0] symbol_trigger;
    wire valid_out;

    // Instantiate UUT
    // Using shorter parameters for simulation speed
    // DWELL: 3 cycles, COOLDOWN: 5 cycles
    boreal_symbolic_mapper #(
        .THRESHOLD_POS(16'd10000),
        .THRESHOLD_NEG(-16'd10000),
        .DWELL_TIME_CYCLES(3),
        .COOLDOWN_CYCLES(5)
    ) uut (
        .clk(clk),
        .rst_n(rst_n),
        .enable(enable),
        .valid_in(valid_in),
        .cursor_x(cursor_x),
        .cursor_y(cursor_y),
        .symbol_trigger(symbol_trigger),
        .valid_out(valid_out)
    );

    // 100MHz clock
    always #5 clk = ~clk;

    // Monitor for Output Triggers
    always @(posedge clk) begin
        if (valid_out) begin
            $display("[PULSE CAUGHT] Symbol Trigger Fired: %b at time %0t", symbol_trigger, $time);
        end
    end

    task apply_cursor;
        input signed [15:0] x;
        input signed [15:0] y;
        begin
            @(posedge clk);
            valid_in = 1;
            cursor_x = x;
            cursor_y = y;
            @(posedge clk);
            valid_in = 0;
            #10;
        end
    endtask

    initial begin
        clk = 0;
        rst_n = 0;
        enable = 0;
        valid_in = 0;
        cursor_x = 0;
        cursor_y = 0;

        $dumpfile("sim/boreal_mapper.vcd");
        $dumpvars(0, tb_boreal_symbolic_mapper);

        #100;
        rst_n = 1;
        #20;
        enable = 1;

        $display("=== BOREAL SYMBOLIC MAPPER SIMULATION ===");

        // -------------------------------------------------------------
        // Test 1: Transient Spike Rejection (False Positive Prevention)
        // Expected: Spikes over the boundary that last < 3 packets should do nothing
        // -------------------------------------------------------------
        $display("--- Test 1: Transient Spike Rejection ---");
        apply_cursor(15000, 0); // Dwell 1
        apply_cursor(15000, 0); // Dwell 2
        apply_cursor(0, 0);     // Slip off boundary. Reset.
        apply_cursor(15000, 0); // Dwell 1
        $display("Test 1 Finished. Should have 0 pulses so far.");

        // -------------------------------------------------------------
        // Test 2: Successful Intent Integration
        // Expected: Holding the boundary for >= 3 packets should fire a single trigger
        // -------------------------------------------------------------
        $display("--- Test 2: Successful Symbol Trigger ---");
        apply_cursor(15000, 0); // Dwell 2
        apply_cursor(15000, 0); // Dwell 3 -> Should PULSE!
        apply_cursor(15000, 0); // Cooldown 1
        $display("Test 2 Finished. Should have caught RIGHT trigger.");

        // -------------------------------------------------------------
        // Test 3: Refractory Cooldown Period
        // Expected: Even while holding the boundary, further triggers are suppressed
        // -------------------------------------------------------------
        $display("--- Test 3: Refractory Cooldown ---");
        apply_cursor(15000, 0); // Cooldown 2
        apply_cursor(15000, 0); // Cooldown 3
        apply_cursor(15000, 0); // Cooldown 4
        apply_cursor(15000, 0); // Cooldown 5 (Cooldown Ends)
        apply_cursor(15000, 0); // Dwell 1 again
        $display("Test 3 Finished. No extra pulses should have fired.");

        // -------------------------------------------------------------
        // Test 4: Re-engage after Cooldown (Different Direction)
        // -------------------------------------------------------------
        $display("--- Test 4: Trigger UP ---");
        apply_cursor(0, 15000); // Dwell 1
        apply_cursor(0, 15000); // Dwell 2
        apply_cursor(0, 15000); // Dwell 3 -> Should PULSE!
        $display("Test 4 Finished. Should have caught UP trigger.");

        $display("=== SIMULATION COMPLETE ===");
        $finish;
    end

endmodule

boreal bci 2/boreal_neuro_core_v2.4/sim/boreal_mapper.vcd
$date
	Tue Feb 24 14:47:43 2026
$end
$version
	Icarus Verilog
$end
$timescale
	1ps
$end
$scope module tb_boreal_symbolic_mapper $end
$var wire 1 ! valid_out $end
$var wire 4 " symbol_trigger [3:0] $end
$var reg 1 # clk $end
$var reg 16 $ cursor_x [15:0] $end
$var reg 16 % cursor_y [15:0] $end
$var reg 1 & enable $end
$var reg 1 ' rst_n $end
$var reg 1 ( valid_in $end
$scope module uut $end
$var wire 1 # clk $end
$var wire 16 ) cursor_x [15:0] $end
$var wire 16 * cursor_y [15:0] $end
$var wire 1 & enable $end
$var wire 1 ' rst_n $end
$var wire 1 ( valid_in $end
$var wire 1 + cross_up $end
$var wire 1 , cross_right $end
$var wire 1 - cross_left $end
$var wire 1 . cross_down $end
$var parameter 32 / COOLDOWN_CYCLES $end
$var parameter 32 0 DWELL_TIME_CYCLES $end
$var parameter 3 1 STATE_COOLDOWN $end
$var parameter 3 2 STATE_IDLE $end
$var parameter 3 3 STATE_INTEGRATE $end
$var parameter 3 4 STATE_TRIGGER $end
$var parameter 16 5 THRESHOLD_NEG $end
$var parameter 16 6 THRESHOLD_POS $end
$var reg 4 7 active_target [3:0] $end
$var reg 16 8 cooldown_counter [15:0] $end
$var reg 16 9 dwell_counter [15:0] $end
$var reg 3 : state [2:0] $end
$var reg 4 ; symbol_trigger [3:0] $end
$var reg 1 ! valid_out $end
$upscope $end
$scope task apply_cursor $end
$var reg 16 < x [15:0] $end
$var reg 16 = y [15:0] $end
$upscope $end
$upscope $end
$enddefinitions $end
$comment Show the parameter values. $end
$dumpall
b10011100010000 6
b1101100011110000 5
b10 4
b1 3
b0 2
b11 1
b11 0
b101 /
$end
#0
$dumpvars
bx =
bx <
b0 ;
b0 :
b0 9
b0 8
b0 7
0.
0-
0,
0+
b0 *
b0 )
0(
0'
0&
b0 %
b0 $
0#
b0 "
0!
$end
#5000
1#
#10000
0#
#15000
1#
#20000
0#
#25000
1#
#30000
0#
#35000
1#
#40000
0#
#45000
1#
#50000
0#
#55000
1#
#60000
0#
#65000
1#
#70000
0#
#75000
1#
#80000
0#
#85000
1#
#90000
0#
#95000
1#
#100000
0#
1'
#105000
1#
#110000
0#
#115000
1#
#120000
0#
b0 =
b11101010011000 <
1&
#125000
b1 7
1,
b11101010011000 $
b11101010011000 )
1(
1#
#130000
0#
#135000
0(
1#
#140000
0#
#145000
b1 :
b1 9
1(
1#
#150000
0#
#155000
0(
1#
#160000
0#
#165000
b0 :
b0 9
b0 7
0,
b0 $
b0 )
1(
1#
b0 <
#170000
0#
#175000
0(
1#
#180000
0#
#185000
b1 7
1,
b11101010011000 $
b11101010011000 )
1(
1#
b11101010011000 <
#190000
0#
#195000
0(
1#
#200000
0#
#205000
b1 :
b1 9
1(
1#
#210000
0#
#215000
0(
1#
#220000
0#
#225000
b10 9
1(
1#
#230000
0#
#235000
0(
1#
#240000
0#
#245000
b11 :
1!
b1 "
b1 ;
1(
1#
#250000
0#
#255000
0!
b0 "
b0 ;
0(
1#
#260000
0#
#265000
b1 8
1(
1#
#270000
0#
#275000
0(
1#
#280000
0#
#285000
b10 8
1(
1#
#290000
0#
#295000
0(
1#
#300000
0#
#305000
b11 8
1(
1#
#310000
0#
#315000
0(
1#
#320000
0#
#325000
b100 8
1(
1#
#330000
0#
#335000
0(
1#
#340000
0#
#345000
b101 8
1(
1#
#350000
0#
#355000
0(
1#
#360000
0#
#365000
b0 7
b0 :
1+
b11101010011000 %
b11101010011000 *
0,
b0 $
b0 )
1(
1#
b11101010011000 =
b0 <
#370000
0#
#375000
0(
1#
#380000
0#
#385000
b1000 7
1(
1#
#390000
0#
#395000
0(
1#
#400000
0#
#405000
b1 :
b1 9
1(
1#
#410000
0#
#415000
0(
1#
